{
  "subtitle": "", 
  "description": "", 
  "language": "fre_FR", 
  "title": "Qu'est-ce que U-Report ?", 
  "primary_category": "75b70b8bf75741e293d4b13bcae76755", 
  "created_at": "2016-06-23T14:07:06+00:00", 
  "featured_in_category": true, 
  "modified_at": "2016-06-23T18:15:21.632201+00:00", 
  "_version": {
    "package_version": "1.4.4", 
    "language_version": "2.7.6", 
    "language": "python", 
    "language_version_string": "2.7.6 (default, Jun 22 2015, 18:01:27) \n[GCC 4.8.2]", 
    "package": "elastic-git"
  }, 
  "linked_pages": [], 
  "id": null, 
  "content": "**U-Report** est un outil gratuit de communication par SMS ayant pour but d'engager nos communaut\u00e9s \u00e0 s'interroger, \u00e0 d\u00e9battre et \u00e0 se faire entendre sur les probl\u00e8mes qui nous concerne en tant que S\u00e9n\u00e9galais et en tant que jeunes.", 
  "source": null, 
  "featured": true, 
  "author_tags": [], 
  "image": null, 
  "published": null, 
  "position": 0, 
  "image_host": "http://thumbor.unicore.io", 
  "slug": "quest-ce-que-u-report", 
  "uuid": "d58bd8bcc701476e8a458c56e507bc4b"
}